any_utils/__init__.py
any_utils/metrics.py
asyncio_payok/__init__.py
asyncio_payok/api.py
asyncio_payok/base.py
asyncio_payok/concrete.py
asyncio_payok/operations.py
asyncio_payok/payok_base.py
asyncio_payok/const/__init__.py
asyncio_payok/const/en.py
asyncio_payok/const/enums.py
asyncio_payok/const/ex.py
asyncio_payok/const/models.py
asyncio_payok-1.0.0.dist-info/METADATA
asyncio_payok-1.0.0.dist-info/WHEEL
asyncio_payok-1.0.0.dist-info/top_level.txt
asyncio_payok-1.0.0.dist-info/RECORD
