Metadata-Version: 2.1
Name: asyncio_payok
Version: 1.0.0
Summary: Asyncio client for PayOk API
Home-page: https://github.com/slimeless/asycncio-payok
Author: Abracadabra
Author-email: stopcrybby@gmail.com
Requires-Python: >=3.6
Requires-Dist: aiohttp
Requires-Dist: pydantic
